napari_pims_bioformats/__init__.py
napari_pims_bioformats/_version.py
napari_pims_bioformats/pims.py
napari_pims_bioformats/_tests/__init__.py
napari_pims_bioformats/_tests/test_pims.py
napari_pims_bioformats-0.0.1.dist-info/LICENSE
napari_pims_bioformats-0.0.1.dist-info/METADATA
napari_pims_bioformats-0.0.1.dist-info/WHEEL
napari_pims_bioformats-0.0.1.dist-info/entry_points.txt
napari_pims_bioformats-0.0.1.dist-info/top_level.txt
napari_pims_bioformats-0.0.1.dist-info/RECORD
